Metadata-Version: 2.1
Name: odoo12-addon-helpdesk-mgmt-timesheet-time-control
Version: 12.0.1.0.0.99.dev10
Summary: Helpdesk Management Timesheet Time Control
Home-page: https://o4sb.com
Author: Graeme Gellatly,Odoo Community Association (OCA)
Author-email: support@odoo-community.org
License: AGPL-3
Platform: UNKNOWN
Classifier: Programming Language :: Python
Classifier: Framework :: Odoo
Classifier: Framework :: Odoo :: 12.0
Classifier: License :: OSI Approved :: GNU Affero General Public License v3
Requires-Python: >=3.5
Requires-Dist: odoo12-addon-helpdesk-mgmt-project
Requires-Dist: odoo12-addon-helpdesk-mgmt-timesheet
Requires-Dist: odoo12-addon-project-timesheet-time-control
Requires-Dist: odoo <12.1dev,>=12.0a
